hexo_mcp_server/__init__.py
hexo_mcp_server/server.py
hexo_mcp_server/utils.py
hexo_mcp_server-0.1.0.dist-info/METADATA
hexo_mcp_server-0.1.0.dist-info/WHEEL
hexo_mcp_server-0.1.0.dist-info/entry_points.txt
hexo_mcp_server-0.1.0.dist-info/RECORD
