Metadata-Version: 2.4
Name: hexo-mcp-server
Version: 0.1.0
Summary: A mcp server for Hexo
Author-email: powercheng <hczshd@gmail.com>
Requires-Python: >=3.11
Requires-Dist: loguru>=0.7.3
Requires-Dist: mcp[cli]>=1.9.3
